[
  {
    "name": "login",
    "path": "/login",
    "component": "C:\\\\xampp\\\\htdocs\\\\biggofinal\\\\pages\\\\login.vue",
    "chunkName": "pages/login",
    "_name": "_8dbe946e"
  },
  {
    "name": "profileFilter",
    "path": "/profileFilter",
    "component": "C:\\\\xampp\\\\htdocs\\\\biggofinal\\\\pages\\\\profileFilter.vue",
    "chunkName": "pages/profileFilter",
    "_name": "_86495e3e"
  },
  {
    "name": "profiles-id",
    "path": "/profiles/:id?",
    "component": "C:\\\\xampp\\\\htdocs\\\\biggofinal\\\\pages\\\\profiles\\\\_id.vue",
    "chunkName": "pages/profiles/_id",
    "_name": "_5762ff70"
  },
  {
    "name": "index",
    "path": "/",
    "component": "C:\\\\xampp\\\\htdocs\\\\biggofinal\\\\pages\\\\index.vue",
    "chunkName": "pages/index",
    "_name": "_210dda9c"
  },
  {
    "name": "name",
    "path": "/:name",
    "component": "C:\\\\xampp\\\\htdocs\\\\biggofinal\\\\pages\\\\_name.vue",
    "chunkName": "pages/_name",
    "_name": "_da95dd6c"
  }
]
